AUTHORS
MANIFEST.in
README.creole
setup.py
cli_scripts/README.creole
cli_scripts/login_info.py
django_kippo/__init__.py
django_kippo/admin.py
django_kippo/models.py
django_kippo.egg-info/PKG-INFO
django_kippo.egg-info/SOURCES.txt
django_kippo.egg-info/dependency_links.txt
django_kippo.egg-info/not-zip-safe
django_kippo.egg-info/requires.txt
django_kippo.egg-info/top_level.txt
django_kippo_test_project/README.creole
django_kippo_test_project/__init__.py
django_kippo_test_project/manage.py
django_kippo_test_project/settings.py
django_kippo_test_project/urls.py