Metadata-Version: 1.1
Name: django-kippo
Version: 0.1.0.0707
Summary: Django App for kippo SSH Honeypot
Home-page: https://github.com/jedie/django-kippo/
Author: Jens Diemer
Author-email: django-kippo@jensdiemer.de
License: UNKNOWN
Download-URL: http://pypi.python.org/pypi/django-kippo/
Keywords: django,kippo,SSH,honeypot
Platform: UNKNOWN
Classifier: Development Status :: 4 - Beta
Classifier: Environment :: Web Environment
Classifier: Intended Audience :: Developers
Classifier: License :: OSI Approved :: GNU General Public License (GPL)
Classifier: Programming Language :: Python
Classifier: Framework :: Django
Classifier: Topic :: Database :: Front-Ends
Classifier: Topic :: Documentation
Classifier: Topic :: Internet :: WWW/HTTP :: Dynamic Content
Classifier: Topic :: Internet :: WWW/HTTP :: Site Management
Classifier: Topic :: Internet :: WWW/HTTP :: WSGI :: Application
Classifier: Operating System :: OS Independent
